richcolorlog/__init__.py
richcolorlog/__main__.py
richcolorlog/__version__.py
richcolorlog/color_support.py
richcolorlog/colors_check.py
richcolorlog/example_usage.py
richcolorlog/logger.py
richcolorlog/screenshot.png
richcolorlog/test.py
richcolorlog/test_check.py
richcolorlog/test_lexer.py
richcolorlog/test_setup_logging.py
richcolorlog/test_setup_logging_custom.py
richcolorlog/test_show_type.py
richcolorlog/test_simple_lexer.py
richcolorlog-1.44.32.dist-info/licenses/LICENSE
richcolorlog-1.44.32.dist-info/METADATA
richcolorlog-1.44.32.dist-info/WHEEL
richcolorlog-1.44.32.dist-info/entry_points.txt
richcolorlog-1.44.32.dist-info/top_level.txt
richcolorlog-1.44.32.dist-info/RECORD
