Metadata-Version: 2.4
Name: richcolorlog
Version: 1.44.32
Summary: A beautiful and feature-rich logging package using Rich library
Home-page: https://github.com/cumulus13/richcolorlog
Author: Hadi Cahyadi
Author-email: Hadi Cahyadi <cumulus13@gmail.com>
Maintainer-email: Hadi Cahyadi <cumulus13@gmail.com>
License: MIT
Project-URL: Homepage, https://github.com/cumulus13/richcolorlog
Project-URL: Repository, https://github.com/cumulus13/richcolorlog
Project-URL: Documentation, https://richcolorlog.readthedocs.io
Project-URL: Bug Tracker, https://github.com/cumulus13/richcolorlog/issues
Keywords: logging,rich,console,terminal,colors,formatting
Classifier: Development Status :: 4 - Beta
Classifier: Intended Audience :: Developers
Classifier: Operating System :: OS Independent
Classifier: Programming Language :: Python :: 3
Classifier: Programming Language :: Python :: 3.7
Classifier: Programming Language :: Python :: 3.8
Classifier: Programming Language :: Python :: 3.9
Classifier: Programming Language :: Python :: 3.10
Classifier: Programming Language :: Python :: 3.11
Classifier: Programming Language :: Python :: 3.12
Classifier: Topic :: Software Development :: Libraries :: Python Modules
Classifier: Topic :: System :: Logging
Classifier: Topic :: Utilities
Requires-Python: >=3.7
License-File: LICENSE
Requires-Dist: rich>=10.0.0
Provides-Extra: dev
Requires-Dist: pytest>=6.0; extra == "dev"
Requires-Dist: pytest-cov; extra == "dev"
Requires-Dist: black; extra == "dev"
Requires-Dist: flake8; extra == "dev"
Requires-Dist: mypy; extra == "dev"
Dynamic: author
Dynamic: home-page
Dynamic: license-file
Dynamic: requires-python
